atcoder_submit_status/__about__.py
atcoder_submit_status/__init__.py
atcoder_submit_status/fetch.py
atcoder_submit_status/log_formatter.py
atcoder_submit_status/login.py
atcoder_submit_status/logout.py
atcoder_submit_status/main.py
atcoder_submit_status/service.py
atcoder_submit_status/utils.py
atcoder_submit_status/watch.py
atcoder_submit_status-0.0.4.dist-info/LICENSE
atcoder_submit_status-0.0.4.dist-info/METADATA
atcoder_submit_status-0.0.4.dist-info/WHEEL
atcoder_submit_status-0.0.4.dist-info/entry_points.txt
atcoder_submit_status-0.0.4.dist-info/top_level.txt
atcoder_submit_status-0.0.4.dist-info/RECORD
