Metadata-Version: 2.1
Name: atcoder-submit-status
Version: 0.0.4
Summary: CLI tool to fetch atcoder-submit-status
Home-page: https://github.com/ngng628/atcoder-submit-status
Author: ngng628
Author-email: ngng628.kyopro@gmail.com
License: MIT License
Keywords: atcoder
Platform: UNKNOWN
Classifier: Environment :: Console
Classifier: Topic :: Utilities
Classifier: License :: OSI Approved :: MIT License
Classifier: Programming Language :: Python :: 3
Classifier: Topic :: Internet :: WWW/HTTP
Requires-Python: >=3.6
Requires-Dist: Pygments (>=2.13.0)
Requires-Dist: appdirs (>=1.4.4)
Requires-Dist: beautifulsoup4 (>=4.11.1)
Requires-Dist: bs4 (>=0.0.1)
Requires-Dist: certifi (>=2022.9.24)
Requires-Dist: charset-normalizer (>=2.1.1)
Requires-Dist: colorama (>=0.4.5)
Requires-Dist: commonmark (>=0.9.1)
Requires-Dist: idna (>=3.4)
Requires-Dist: lxml (>=4.9.1)
Requires-Dist: requests (>=2.28.1)
Requires-Dist: rich (>=12.6.0)
Requires-Dist: soupsieve (>=2.3.2.post1)
Requires-Dist: urllib3 (>=1.26.12)
